LICENSE
README.md
setup.py
secury_code/__init__.py
secury_code/secury_lib.py
secury_code.egg-info/PKG-INFO
secury_code.egg-info/SOURCES.txt
secury_code.egg-info/dependency_links.txt
secury_code.egg-info/requires.txt
secury_code.egg-info/top_level.txt