Metadata-Version: 2.1
Name: secury-code
Version: 0.0.2
Summary: Welcome to Secury Code
Home-page: UNKNOWN
Author: LowDevelop
Author-email: lowdevlop@gmail.com
License: MIT License
Keywords: secury code
Platform: UNKNOWN
